README.md
scripts/dashboard.py
scripts/run_controller.py
pwb_alphaevolve-0.1.0.dist-info/METADATA
pwb_alphaevolve-0.1.0.dist-info/WHEEL
pwb_alphaevolve-0.1.0.dist-info/entry_points.txt
pwb_alphaevolve-0.1.0.dist-info/RECORD
