Metadata-Version: 2.4
Name: pwb-alphaevolve
Version: 0.1.0
Summary: Autonomous evolution of algorithmic‑trading strategies using Backtrader, Papers With Backtest data, and OpenAI LLMs.
Project-URL: Homepage, https://github.com/your-org/pwb-alphaevolve
Project-URL: Issues, https://github.com/your-org/pwb-alphaevolve/issues
Author-email: AlphaEvolve Contributors <hello@paperswithbacktest.com>
License: MIT
Keywords: LLM,algorithmic‑trading,backtesting,backtrader,evolution
Classifier: Intended Audience :: Developers
Classifier: License :: OSI Approved :: MIT License
Classifier: Programming Language :: Python :: 3
Classifier: Programming Language :: Python :: 3 :: Only
Classifier: Programming Language :: Python :: 3.10
Classifier: Topic :: Office/Business :: Financial :: Investment
Requires-Python: >=3.10
Requires-Dist: backoff>=2.2
Requires-Dist: backtrader>=1.9
Requires-Dist: numpy
Requires-Dist: openai>=1.0
Requires-Dist: pandas>=2.0
Requires-Dist: pwb-backtrader>=1.9.78.123
Requires-Dist: pwb-toolbox>=0.1.2
Requires-Dist: pydantic>=2.0
Requires-Dist: python-dateutil
Requires-Dist: tqdm
Provides-Extra: dashboard
Requires-Dist: matplotlib>=3.8; extra == 'dashboard'
Requires-Dist: streamlit>=1.30; extra == 'dashboard'
Provides-Extra: dev
Requires-Dist: black>=24.3; extra == 'dev'
Requires-Dist: ipykernel; extra == 'dev'
Requires-Dist: pre-commit>=3.0; extra == 'dev'
Requires-Dist: pytest>=8.0; extra == 'dev'
Requires-Dist: ruff>=0.4; extra == 'dev'
